jexchange_mcp_server/__init__.py
jexchange_mcp_server/__main__.py
jexchange_mcp_server/server.py
jexchange_mcp_server-0.1.0.dist-info/METADATA
jexchange_mcp_server-0.1.0.dist-info/WHEEL
jexchange_mcp_server-0.1.0.dist-info/entry_points.txt
jexchange_mcp_server-0.1.0.dist-info/RECORD
